SecQureSdk/__init__.py
SecQureSdk/accessToken.py
SecQureSdk/idToken.py
SecQureSdk/renewToken.py
pySdk/__init__.py
pySdk/accessToken.py
pySdk/idToken.py
pySdk/renewToken.py
secuuthSdk/__init__.py
secuuthSdk/accessToken.py
secuuthSdk/idToken.py
secuuthSdk/renewToken.py
SecQurePySdk-3.4.dist-info/LICENSE
SecQurePySdk-3.4.dist-info/METADATA
SecQurePySdk-3.4.dist-info/WHEEL
SecQurePySdk-3.4.dist-info/top_level.txt
SecQurePySdk-3.4.dist-info/RECORD
