Metadata-Version: 2.1
Name: SecQurePySdk
Version: 3.4
Summary: secuuth  SDK for python scripts
Home-page: https://github.com/engineering-secuuth/secuuth-jwt-python-sdk
Author: secuuth
Author-email: amitoshkumar10@gmail.com
License: UNKNOWN
Platform: UNKNOWN
Classifier: Programming Language :: Python :: 3
Classifier: License :: OSI Approved :: MIT License
Classifier: Operating System :: OS Independent
License-File: LICENSE
Requires-Dist: requests
Requires-Dist: python-jose
